phaxio/exceptions.py
phaxio/api.py
phaxio/utils.py
phaxio/__init__.py
tests/test_api.py
tests/test_errors.py
tests/__init__.py
pyphaxio-0.11.dist-info/WHEEL
pyphaxio-0.11.dist-info/metadata.json
pyphaxio-0.11.dist-info/DESCRIPTION.rst
pyphaxio-0.11.dist-info/top_level.txt
pyphaxio-0.11.dist-info/METADATA
pyphaxio-0.11.dist-info/RECORD
