Metadata-Version: 2.0
Name: pyphaxio
Version: 0.11
Summary: Python client for Phaxio
Home-page: https://github.com/jfialkoff/pyphaxio
Author: Joshua Fialkoff
Author-email: joshua.fialkoff@setaris.com
License: MIT License
Keywords: python phaxio fax api
Platform: UNKNOWN
Requires-Dist: requests
